dazpycheck/__init__.py
dazpycheck/main.py
dazpycheck/main_test.py
dazpycheck-0.13.0.dist-info/METADATA
dazpycheck-0.13.0.dist-info/WHEEL
dazpycheck-0.13.0.dist-info/entry_points.txt
dazpycheck-0.13.0.dist-info/top_level.txt
dazpycheck-0.13.0.dist-info/RECORD
