Metadata-Version: 2.4
Name: dazpycheck
Version: 0.13.0
Summary: A tool to check and validate a Python code repository.
Author-email: Darren Oakey <darren@oakey.net>
Classifier: Programming Language :: Python :: 3
Classifier: License :: OSI Approved :: MIT License
Classifier: Operating System :: OS Independent
Requires-Python: >=3.7
